drb_impl_webdav/__init__.py
drb_impl_webdav/_version.py
drb_impl_webdav/cortex.yml
drb_impl_webdav/drb_impl_webdav.py
drb_impl_webdav/utility_auth.py
drb_impl_webdav-1.0.0.data/data/requirements.txt
drb_impl_webdav-1.0.0.dist-info/METADATA
drb_impl_webdav-1.0.0.dist-info/WHEEL
drb_impl_webdav-1.0.0.dist-info/entry_points.txt
drb_impl_webdav-1.0.0.dist-info/top_level.txt
drb_impl_webdav-1.0.0.dist-info/RECORD
