Metadata-Version: 2.1
Name: drb-impl-webdav
Version: 1.0.0
Summary: DRB Web-based Distributed Authoring and Versioning implementation
Home-page: https://gitlab.com/drb-python/impl/webdav
Author: GAEL Systems
Author-email: drb-python@gael.fr
License: UNKNOWN
Platform: UNKNOWN
Classifier: Programming Language :: Python :: 3.8
Classifier: License :: OSI Approved :: Apache Software License
Classifier: Operating System :: OS Independent
Requires-Python: >=3.8
Requires-Dist: webdavclient3 (==3.14.6)
Requires-Dist: drb (<1.1.0,>=1.0.1)
Requires-Dist: requests (==2.27.1)
